patchworklib/__init__.py
patchworklib/modified_grid.py
patchworklib/modified_plotnine.py
patchworklib/patchworklib.py
patchworklib-0.6.4.dist-info/LICENSE
patchworklib-0.6.4.dist-info/METADATA
patchworklib-0.6.4.dist-info/WHEEL
patchworklib-0.6.4.dist-info/top_level.txt
patchworklib-0.6.4.dist-info/RECORD
