Metadata-Version: 2.1
Name: patchworklib
Version: 0.6.4
Summary: patchwork for matplotlib
Home-page: https://github.com/ponnhide/patchworklib
Download-URL: https://github.com/ponnhide/patchworklib
Author: Hideto Mori
Author-email: hidto7592@gmail.com
Maintainer: Hideto Mori
Maintainer-email: hidto7592@gmail.com
License: GNU General Public License v3.0
Classifier: Intended Audience :: Science/Research
Classifier: Programming Language :: Python :: 3.7
Classifier: Programming Language :: Python :: 3.8
Classifier: Programming Language :: Python :: 3.9
Classifier: Programming Language :: Python :: 3.10
Classifier: License :: OSI Approved :: GNU General Public License v3 (GPLv3)
Requires-Python: >=3.7
License-File: LICENSE
Requires-Dist: matplotlib (>=3.4)
Requires-Dist: pandas (>=0.24)
Requires-Dist: numpy (>=1.16)
Requires-Dist: dill
Requires-Dist: seaborn
Requires-Dist: plotnine (<=0.12.4)
